lxbtools.py
lxbtools-1.1.dist-info/METADATA
lxbtools-1.1.dist-info/WHEEL
lxbtools-1.1.dist-info/top_level.txt
lxbtools-1.1.dist-info/RECORD
