Metadata-Version: 2.1
Name: lxbtools
Version: 1.1
Summary: Common tools
Home-page: https://gitee.com/liuxiaobopro/lxbtools
Author: liuxiaobo
Author-email: 1369924600@qq.com
License: MIT
Platform: UNKNOWN
